{"warId":801,"startDate":1706040313,"endDate":1833653095,"layoutVersion":464,"minimumClientVersion":"0.3.0","planetInfos":[{"index":0,"settingsHash":897386910,"planetNameId32":0,"position":{"x":0,"y":0},"waypoints":[],"sector":0,"maxHealth":1000000,"disabled":false,"initialOwner":1},{"index":1,"settingsHash":3621417917,"planetNameId32":0,"position":{"x":0.05373042,"y":0.10565466},"waypoints":[],"sector":1,"maxHealth":1000000,"disabled":false,"initialOwner":1},{"index":2,"settingsHash":2543303604,"planetNameId32":0,"position":{"x":0.04664221,"y":0.16758725},"waypoints":[],"sector":1,"maxHealth":1000000,"disabled":false,"initialOwner":1},{"index":3,"settingsHash":2768073863,"planetNameId32":0,"position":{"x":0.12536779,"y":0.11821219},"waypoints":[],"sector":1,"maxHealth":1000000,"disabled":false,"initialOwner":1},{"index":4,"settingsHash":158585041,"planetNameId32":0,"position":{"x":0.10280278,"y":0.05765711},"waypoints":[],"sector":1,"maxHealth":1000000,"disabled":false,"initialOwner":1},{"index":5,"settingsHash":1008084099,"planetNameId32":0,"position":{"x":0.15988354,"y":0.043583166},"waypoints":[],"sector":1,"maxHealth":1000000,"disabled":false,"initialOwner":1},{"index":6,"settingsHash":167872110,"planetNameId32":0,"position":{"x":0.13535836,"y":-0.03378948},"waypoints":[],"sector":2,"maxHealth":1000000,"disabled":false,"initialOwner":1},{"index":7,"settingsHash":1138804949,"planetNameId32":0,"position":{"x":0.36159223,"y":-0.52270126},"waypoints":[178],"sector":2,"maxHealth":1700000,"disabled":false,"initialOwner":1},{"index":8,"settingsHash":3550298780,"planetNameId32":0,"position":{"x":0.09485684,"y":-0.08101245},"waypoints":[],"sector":2,"maxHealth":1000000,"disabled":false,"initialOwner":1},{"index":9,"settingsHash":1025193891,"planetNameId32":0,"position":{"x":0.15801243,"y":-0.09685686},"waypoints":[],"sector":2,"maxHealth":1000000,"disabled":false,"initialOwner":1},{"index":10,"settingsHash":2767954873,"planetNameId32":0,"position":{"x":0.06770126,"y":-0.1448935},"waypoints":[],"sector":2,"maxHealth":1000000,"disabled":false,"initialOwner":1},{"index":11,"settingsHash":688773671,"planetNameId32":0,"position":{"x":0.001789452,"y":-0.18935835},"waypoints":[],"sector":3,"maxHealth":1000000,"disabled":false,"initialOwner":1},{"index":12,"settingsHash":160818366,"planetNameId32":0,"position":{"x":-0.001789474,"y":-0.12535837},"waypoints":[],"sector":3,"maxHealth":1000000,"disabled":false,"initialOwner":1},{"index":13,"settingsHash":2877873656,"planetNameId32":0,"position":{"x":-0.06158319,"y":-0.16488354},"waypoints":[],"sector":4,"maxHealth":1000000,"disabled":false,"initialOwner":1},{"index":14,"settingsHash":1529228469,"planetNameId32":0,"position":{"x":-0.099012464,"y":-0.11185683},"waypoints":[],"sector":5,"maxHealth":1000000,"disabled":false,"initialOwner":1},{"index":15,"settingsHash":3749877391,"planetNameId32":0,"position":{"x":-0.17010404,"y":-0.08865711},"waypoints":[],"sector":5,"maxHealth":1000000,"disabled":false,"initialOwner":1},{"index":16,"settingsHash":4254371037,"planetNameId32":0,"position":{"x":0.27240774,"y":0.20429876},"waypoints":[77],"sector":5,"maxHealth":1000000,"disabled":false,"initialOwner":1},{"index":17,"settingsHash":2273175182,"planetNameId32":0,"position":{"x":-0.14765465,"y":-0.030730395},"waypoints":[],"sector":5,"maxHealth":1000000,"disabled":false,"initialOwner":1},{"index":18,"settingsHash":3088889549,"planetNameId32":0,"position":{"x":-0.15065464,"y":0.015730456},"waypoints":[],"sector":6,"maxHealth":1000000,"disabled":false,"initialOwner":1},{"index":19,"settingsHash":768352347,"planetNameId32":0,"position":{"x":-0.1728935,"y":0.06970126},"waypoints":[],"sector":7,"maxHealth":1000000,"disabled":false,"initialOwner":1},{"index":20,"settingsHash":1299274778,"planetNameId32":0,"position":{"x":-0.12621213,"y":0.11136782},"waypoints":[],"sector":7,"maxHealth":1000000,"disabled":false,"initialOwner":1},{"index":21,"settingsHash":3992185257,"planetNameId32":0,"position":{"x":-0.07801243,"y":0.10585686},"waypoints":[],"sector":7,"maxHealth":1000000,"disabled":false,"initialOwner":1},{"index":22,"settingsHash":160106209,"planetNameId32":0,"position":{"x":-0.039789412,"y":0.14535835},"waypoints":[],"sector":7,"maxHealth":1000000,"disabled":false,"initialOwner":1},{"index":23,"settingsHash":1257502272,"planetNameId32":0,"position":{"x":0.030315775,"y":0.2269306},"waypoints":[],"sector":8,"maxHealth":1000000,"disabled":false,"initialOwner":1},{"index":24,"settingsHash":2862366365,"planetNameId32":0,"position":{"x":0.09383544,"y":0.25608748},"waypoints":[],"sector":8,"maxHealth":1000000,"disabled":false,"initialOwner":1},{"index":25,"settingsHash":1812451556,"planetNameId32":0,"position":{"x":0.17009519,"y":0.1877717},"waypoints":[49],"sector":9,"maxHealth":1000000,"disabled":false,"initialOwner":1},{"index":26,"settingsHash":4068066596,"planetNameId32":0,"position":{"x":0.2117717,"y":0.12409518},"waypoints":[16,25,27],"sector":9,"maxHealth":1000000,"disabled":false,"initialOwner":1},{"index":27,"settingsHash":2585302931,"planetNameId32":0,"position":{"x":0.2540875,"y":0.05583542},"waypoints":[29],"sector":9,"maxHealth":1000000,"disabled":false,"initialOwner":1},{"index":28,"settingsHash":3650236983,"planetNameId32":0,"position":{"x":0.2939306,"y":-0.033684243},"waypoints":[53,81],"sector":9,"maxHealth":2000000,"disabled":false,"initialOwner":1},{"index":29,"settingsHash":410562438,"planetNameId32":0,"position":{"x":0.22952318,"y":-0.029197697},"waypoints":[28],"sector":10,"maxHealth":2500000,"disabled":false,"initialOwner":1},{"index":30,"settingsHash":3538905431,"planetNameId32":0,"position":{"x":0.23037383,"y":-0.0976583},"waypoints":[],"sector":2,"maxHealth":1000000,"disabled":false,"initialOwner":1},{"index":31,"settingsHash":529527934,"planetNameId32":0,"position":{"x":0.2007717,"y":-0.1490952},"waypoints":[],"sector":2,"maxHealth":1000000,"disabled":false,"initialOwner":1},{"index":32,"settingsHash":3945891756,"planetNameId32":0,"position":{"x":0.15409517,"y":-0.210073},"waypoints":[55],"sector":3,"maxHealth":1000000,"disabled":false,"initialOwner":1},{"index":33,"settingsHash":3266374354,"planetNameId32":0,"position":{"x":0.0977173,"y":-0.22407754},"waypoints":[32,56],"sector":3,"maxHealth":2300000,"disabled":false,"initialOwner":1},{"index":34,"settingsHash":3551496165,"planetNameId32":0,"position":{"x":0.5111386,"y":0.3511805},"waypoints":[125,169,212],"sector":3,"maxHealth":1000000,"disabled":false,"initialOwner":2},{"index":35,"settingsHash":2640422831,"planetNameId32":0,"position":{"x":-0.023138678,"y":-0.24981944},"waypoints":[33,36,58],"sector":3,"maxHealth":1000000,"disabled":false,"initialOwner":1},{"index":36,"settingsHash":3407890530,"planetNameId32":0,"position":{"x":-0.09065833,"y":-0.2413738},"waypoints":[37,59],"sector":4,"maxHealth":1700000,"disabled":false,"initialOwner":1},{"index":37,"settingsHash":760056919,"planetNameId32":0,"position":{"x":-0.1440952,"y":-0.2027717},"waypoints":[60],"sector":4,"maxHealth":2000000,"disabled":false,"initialOwner":1},{"index":38,"settingsHash":1831450049,"planetNameId32":0,"position":{"x":-0.19187985,"y":-0.14480585},"waypoints":[37],"sector":5,"maxHealth":1000000,"disabled":false,"initialOwner":1},{"index":39,"settingsHash":298165685,"planetNameId32":0,"position":{"x":-0.24438877,"y":-0.10283538},"waypoints":[38],"sector":5,"maxHealth":1000000,"disabled":false,"initialOwner":1},{"index":40,"settingsHash":2146401321,"planetNameId32":0,"position":{"x":-0.2415232,"y":-0.033197638},"waypoints":[],"sector":6,"maxHealth":1000000,"disabled":false,"initialOwner":1},{"index":41,"settingsHash":3508924100,"planetNameId32":0,"position":{"x":-0.25681943,"y":0.030138722},"waypoints":[],"sector":6,"maxHealth":1000000,"disabled":false,"initialOwner":1},{"index":42,"settingsHash":2243203717,"planetNameId32":0,"position":{"x":-0.2473738,"y":0.09965837},"waypoints":[43,65],"sector":7,"maxHealth":1600000,"disabled":false,"initialOwner":1},{"index":43,"settingsHash":1678797801,"planetNameId32":0,"position":{"x":-0.1857717,"y":0.13809519},"waypoints":[44],"sector":18,"maxHealth":1000000,"disabled":false,"initialOwner":1},{"index":44,"settingsHash":3404343820,"planetNameId32":0,"position":{"x":-0.16809516,"y":0.19577172},"waypoints":[45,66],"sector":18,"maxHealth":2400000,"disabled":false,"initialOwner":1},{"index":45,"settingsHash":2969736642,"planetNameId32":0,"position":{"x":-0.13065825,"y":0.30637383},"waypoints":[68,116],"sector":19,"maxHealth":1000000,"disabled":false,"initialOwner":1},{"index":46,"settingsHash":1438199726,"planetNameId32":0,"position":{"x":-0.061315693,"y":0.2489306},"waypoints":[45,68],"sector":19,"maxHealth":1000000,"disabled":false,"initialOwner":1},{"index":47,"settingsHash":2013504640,"planetNameId32":0,"position":{"x":0.037842084,"y":0.32250285},"waypoints":[],"sector":8,"maxHealth":1000000,"disabled":false,"initialOwner":1},{"index":48,"settingsHash":2525961073,"planetNameId32":0,"position":{"x":0.1129696,"y":0.3345827},"waypoints":[],"sector":8,"maxHealth":1000000,"disabled":false,"initialOwner":1},{"index":49,"settingsHash":2151164116,"planetNameId32":0,"position":{"x":0.2219546,"y":0.2772582},"waypoints":[76],"sector":20,"maxHealth":1000000,"disabled":false,"initialOwner":1},{"index":50,"settingsHash":3265310936,"planetNameId32":0,"position":{"x":0.87390286,"y":0.35359928},"waypoints":[213],"sector":20,"maxHealth":1000000,"disabled":false,"initialOwner":2},{"index":51,"settingsHash":4148701638,"planetNameId32":0,"position":{"x":0.287884,"y":0.1099696},"waypoints":[],"sector":9,"maxHealth":1000000,"disabled":false,"initialOwner":1},{"index":52,"settingsHash":1756822119,"planetNameId32":0,"position":{"x":0.338688,"y":0.05460588},"waypoints":[27,28,80],"sector":9,"maxHealth":1000000,"disabled":false,"initialOwner":1},{"index":53,"settingsHash":438925458,"planetNameId32":0,"position":{"x":0.32650283,"y":-0.12384212},"waypoints":[],"sector":10,"maxHealth":2200000,"disabled":false,"initialOwner":1},{"index":54,"settingsHash":4190033207,"planetNameId32":0,"position":{"x":0.26874065,"y":-0.21253327},"waypoints":[],"sector":11,"maxHealth":1000000,"disabled":false,"initialOwner":1},{"index":55,"settingsHash":3951456049,"planetNameId32":0,"position":{"x":0.19353323,"y":-0.28004193},"waypoints":[88],"sector":12,"maxHealth":1000000,"disabled":false,"initialOwner":1},{"index":56,"settingsHash":207323189,"planetNameId32":0,"position":{"x":0.12696959,"y":-0.30758274},"waypoints":[55,90],"sector":12,"maxHealth":2000000,"disabled":false,"initialOwner":1},{"index":57,"settingsHash":3674393208,"planetNameId32":0,"position":{"x":0.04284205,"y":-0.33550286},"waypoints":[33,56,92],"sector":13,"maxHealth":2000000,"disabled":false,"initialOwner":1},{"index":58,"settingsHash":430094434,"planetNameId32":0,"position":{"x":-0.038842108,"y":-0.32750285},"waypoints":[57,95],"sector":13,"maxHealth":2000000,"disabled":false,"initialOwner":1},{"index":59,"settingsHash":1018677806,"planetNameId32":0,"position":{"x":-0.11379249,"y":-0.3215678},"waypoints":[58,60,96],"sector":14,"maxHealth":1000000,"disabled":false,"initialOwner":1},{"index":60,"settingsHash":2414771368,"planetNameId32":0,"position":{"x":-0.19953328,"y":-0.2830419},"waypoints":[37,98],"sector":14,"maxHealth":1700000,"disabled":false,"initialOwner":1},{"index":61,"settingsHash":635122119,"planetNameId32":0,"position":{"x":-0.26690286,"y":-0.23559926},"waypoints":[38],"sector":15,"maxHealth":1900000,"disabled":false,"initialOwner":1},{"index":62,"settingsHash":3508592390,"planetNameId32":0,"position":{"x":-0.28988406,"y":-0.16096954},"waypoints":[61],"sector":15,"maxHealth":1000000,"disabled":false,"initialOwner":1},{"index":63,"settingsHash":4056948497,"planetNameId32":0,"position":{"x":-0.33550286,"y":-0.05084203},"waypoints":[],"sector":6,"maxHealth":1000000,"disabled":false,"initialOwner":1},{"index":64,"settingsHash":215016124,"planetNameId32":0,"position":{"x":0.2965067,"y":0.11628686},"waypoints":[],"sector":17,"maxHealth":1000000,"disabled":false,"initialOwner":2},{"index":65,"settingsHash":3293929397,"planetNameId32":0,"position":{"x":-0.31756774,"y":0.13179255},"waypoints":[108],"sector":17,"maxHealth":1000000,"disabled":false,"initialOwner":1},{"index":66,"settingsHash":1750606702,"planetNameId32":0,"position":{"x":-0.24490279,"y":0.21259932},"waypoints":[65,113],"sector":18,"maxHealth":1000000,"disabled":false,"initialOwner":1},{"index":67,"settingsHash":3882819373,"planetNameId32":0,"position":{"x":-0.20995454,"y":0.28325823},"waypoints":[45,66],"sector":18,"maxHealth":1300000,"disabled":false,"initialOwner":1},{"index":68,"settingsHash":1223630977,"planetNameId32":0,"position":{"x":-0.05373336,"y":0.3648641},"waypoints":[69],"sector":18,"maxHealth":1000000,"disabled":false,"initialOwner":1},{"index":69,"settingsHash":2115544264,"planetNameId32":0,"position":{"x":-0.060664836,"y":0.44539174},"waypoints":[],"sector":19,"maxHealth":1000000,"disabled":false,"initialOwner":1},{"index":70,"settingsHash":4206815834,"planetNameId32":0,"position":{"x":-0.1716316,"y":0.8050751},"waypoints":[207,253],"sector":8,"maxHealth":1000000,"disabled":false,"initialOwner":1},{"index":71,"settingsHash":2898292715,"planetNameId32":0,"position":{"x":0.0441322,"y":0.42626023},"waypoints":[],"sector":8,"maxHealth":1000000,"disabled":false,"initialOwner":1},{"index":72,"settingsHash":922433838,"planetNameId32":0,"position":{"x":-0.52319145,"y":0.14335436},"waypoints":[109,111],"sector":31,"maxHealth":1600000,"disabled":false,"initialOwner":1},{"index":73,"settingsHash":3238002446,"planetNameId32":0,"position":{"x":0.1661038,"y":0.40307793},"waypoints":[],"sector":8,"maxHealth":1000000,"disabled":false,"initialOwner":1},{"index":74,"settingsHash":670993741,"planetNameId32":0,"position":{"x":0.2559713,"y":0.5260108},"waypoints":[],"sector":20,"maxHealth":1000000,"disabled":false,"initialOwner":1},{"index":75,"settingsHash":2729833133,"planetNameId32":0,"position":{"x":0.372748,"y":0.5082812},"waypoints":[122,123,124],"sector":20,"maxHealth":1000000,"disabled":false,"initialOwner":1},{"index":76,"settingsHash":910588397,"planetNameId32":0,"position":{"x":0.26528117,"y":0.347748},"waypoints":[77,124],"sector":20,"maxHealth":1000000,"disabled":false,"initialOwner":1},{"index":77,"settingsHash":2112907641,"planetNameId32":0,"position":{"x":0.32492584,"y":0.25839266},"waypoints":[49],"sector":20,"maxHealth":1000000,"disabled":false,"initialOwner":1},{"index":78,"settingsHash":1886266372,"planetNameId32":0,"position":{"x":0.6113544,"y":0.22880854},"waypoints":[129,169,170],"sector":21,"maxHealth":1500000,"disabled":false,"initialOwner":2},{"index":79,"settingsHash":1391690878,"planetNameId32":0,"position":{"x":0.39437926,"y":0.27310377},"waypoints":[77,125,168],"sector":21,"maxHealth":1000000,"disabled":false,"initialOwner":2},{"index":80,"settingsHash":3659340575,"planetNameId32":0,"position":{"x":0.43926024,"y":0.0731322},"waypoints":[126],"sector":22,"maxHealth":1800000,"disabled":false,"initialOwner":1},{"index":81,"settingsHash":572365311,"planetNameId32":0,"position":{"x":0.3660751,"y":-0.04763163},"waypoints":[52,53,83],"sector":22,"maxHealth":1300000,"disabled":false,"initialOwner":1},{"index":82,"settingsHash":4009717368,"planetNameId32":0,"position":{"x":0.5340751,"y":-0.090368435},"waypoints":[83,131],"sector":10,"maxHealth":1600000,"disabled":false,"initialOwner":1},{"index":83,"settingsHash":2623879324,"planetNameId32":0,"position":{"x":0.44555652,"y":-0.06207318},"waypoints":[80],"sector":10,"maxHealth":1000000,"disabled":false,"initialOwner":1},{"index":84,"settingsHash":1076755284,"planetNameId32":0,"position":{"x":0.41835436,"y":-0.17080852},"waypoints":[],"sector":24,"maxHealth":1000000,"disabled":false,"initialOwner":1},{"index":85,"settingsHash":912379297,"planetNameId32":0,"position":{"x":0.33707795,"y":0.1548962},"waypoints":[],"sector":24,"maxHealth":1000000,"disabled":false,"initialOwner":1},{"index":86,"settingsHash":2598991571,"planetNameId32":0,"position":{"x":0.39501083,"y":-0.26197135},"waypoints":[],"sector":11,"maxHealth":1000000,"disabled":false,"initialOwner":1},{"index":87,"settingsHash":49391513,"planetNameId32":0,"position":{"x":0.32492584,"y":-0.26339266},"waypoints":[],"sector":11,"maxHealth":1000000,"disabled":false,"initialOwner":1},{"index":88,"settingsHash":2299441253,"planetNameId32":0,"position":{"x":0.24639264,"y":-0.3159259},"waypoints":[89],"sector":12,"maxHealth":1800000,"disabled":false,"initialOwner":1},{"index":89,"settingsHash":2695815635,"planetNameId32":0,"position":{"x":0.29074797,"y":-0.35328123},"waypoints":[90],"sector":12,"maxHealth":1000000,"disabled":false,"initialOwner":1},{"index":90,"settingsHash":1922612740,"planetNameId32":0,"position":{"x":0.18610376,"y":-0.381078},"waypoints":[89],"sector":13,"maxHealth":1900000,"disabled":false,"initialOwner":1},{"index":91,"settingsHash":3172148623,"planetNameId32":0,"position":{"x":0.15380847,"y":-0.4373544},"waypoints":[90,93],"sector":13,"maxHealth":1000000,"disabled":false,"initialOwner":1},{"index":92,"settingsHash":3602852408,"planetNameId32":0,"position":{"x":0.06113215,"y":-0.40526026},"waypoints":[91],"sector":13,"maxHealth":2100000,"disabled":false,"initialOwner":1},{"index":93,"settingsHash":3515684391,"planetNameId32":0,"position":{"x":0.1470731,"y":-0.5095566},"waypoints":[],"sector":13,"maxHealth":1000000,"disabled":false,"initialOwner":1},{"index":94,"settingsHash":997855239,"planetNameId32":0,"position":{"x":0.00063157,"y":-0.4440751},"waypoints":[92,139,140],"sector":13,"maxHealth":1400000,"disabled":false,"initialOwner":1},{"index":95,"settingsHash":910436923,"planetNameId32":0,"position":{"x":-0.07607324,"y":-0.44355652},"waypoints":[94,96,140],"sector":13,"maxHealth":1600000,"disabled":false,"initialOwner":1},{"index":96,"settingsHash":2306843160,"planetNameId32":0,"position":{"x":-0.13786763,"y":-0.40105802},"waypoints":[],"sector":14,"maxHealth":1000000,"disabled":false,"initialOwner":1},{"index":97,"settingsHash":4011448258,"planetNameId32":0,"position":{"x":-0.21110377,"y":-0.42437923},"waypoints":[96,98,99,142],"sector":14,"maxHealth":1000000,"disabled":false,"initialOwner":1},{"index":98,"settingsHash":3533355425,"planetNameId32":0,"position":{"x":-0.25539273,"y":-0.3439258},"waypoints":[],"sector":28,"maxHealth":1000000,"disabled":false,"initialOwner":1},{"index":99,"settingsHash":1616302990,"planetNameId32":0,"position":{"x":-0.31297135,"y":-0.39101082},"waypoints":[144,145],"sector":28,"maxHealth":1000000,"disabled":false,"initialOwner":1},{"index":100,"settingsHash":3515299681,"planetNameId32":0,"position":{"x":0.9189892,"y":-0.1249713},"waypoints":[173,216],"sector":29,"maxHealth":1900000,"disabled":false,"initialOwner":2},{"index":101,"settingsHash":3115954791,"planetNameId32":0,"position":{"x":-0.3422812,"y":-0.302748},"waypoints":[61,98,147],"sector":29,"maxHealth":1000000,"disabled":false,"initialOwner":1},{"index":102,"settingsHash":1017957570,"planetNameId32":0,"position":{"x":-0.4123793,"y":-0.17510368},"waypoints":[61,103],"sector":15,"maxHealth":1000000,"disabled":false,"initialOwner":1},{"index":103,"settingsHash":1398996417,"planetNameId32":0,"position":{"x":-0.353078,"y":-0.13310368},"waypoints":[39,62],"sector":15,"maxHealth":1000000,"disabled":false,"initialOwner":1},{"index":104,"settingsHash":701410047,"planetNameId32":0,"position":{"x":-0.42307508,"y":-0.029368328},"waypoints":[],"sector":16,"maxHealth":1000000,"disabled":false,"initialOwner":1},{"index":105,"settingsHash":2344219187,"planetNameId32":0,"position":{"x":-0.46455657,"y":-0.09407307},"waypoints":[],"sector":16,"maxHealth":1000000,"disabled":false,"initialOwner":1},{"index":106,"settingsHash":1496025116,"planetNameId32":0,"position":{"x":-0.4232602,"y":0.05013234},"waypoints":[108,111],"sector":17,"maxHealth":1000000,"disabled":false,"initialOwner":1},{"index":107,"settingsHash":696145979,"planetNameId32":0,"position":{"x":-0.6355565,"y":0.0490733},"waypoints":[109,155],"sector":17,"maxHealth":1600000,"disabled":false,"initialOwner":1},{"index":108,"settingsHash":435094671,"planetNameId32":0,"position":{"x":-0.349058,"y":0.0568677},"waypoints":[],"sector":31,"maxHealth":1000000,"disabled":false,"initialOwner":1},{"index":109,"settingsHash":2131959183,"planetNameId32":0,"position":{"x":-0.531078,"y":0.05410378},"waypoints":[106],"sector":31,"maxHealth":1000000,"disabled":false,"initialOwner":1},{"index":110,"settingsHash":412801448,"planetNameId32":0,"position":{"x":-0.48401085,"y":0.21397132},"waypoints":[72],"sector":31,"maxHealth":1600000,"disabled":false,"initialOwner":1},{"index":111,"settingsHash":255676170,"planetNameId32":0,"position":{"x":-0.40970957,"y":0.15897132},"waypoints":[65,110],"sector":31,"maxHealth":1000000,"disabled":false,"initialOwner":1},{"index":112,"settingsHash":2442155408,"planetNameId32":0,"position":{"x":-0.26997122,"y":0.3760109},"waypoints":[67,113,194],"sector":32,"maxHealth":1500000,"disabled":false,"initialOwner":1},{"index":113,"settingsHash":3407029244,"planetNameId32":0,"position":{"x":-0.34874794,"y":0.28628126},"waypoints":[],"sector":32,"maxHealth":1000000,"disabled":false,"initialOwner":1},{"index":114,"settingsHash":975759959,"planetNameId32":0,"position":{"x":-0.44310373,"y":0.599078},"waypoints":[159],"sector":19,"maxHealth":1600000,"disabled":false,"initialOwner":1},{"index":115,"settingsHash":101741274,"planetNameId32":0,"position":{"x":-0.27880847,"y":0.58735436},"waypoints":[],"sector":19,"maxHealth":1000000,"disabled":false,"initialOwner":1},{"index":116,"settingsHash":2654907023,"planetNameId32":0,"position":{"x":-0.16213205,"y":0.4142603},"waypoints":[69],"sector":19,"maxHealth":1700000,"disabled":false,"initialOwner":1},{"index":117,"settingsHash":2580049274,"planetNameId32":0,"position":{"x":-0.122073,"y":0.5435566},"waypoints":[161,162],"sector":19,"maxHealth":1200000,"disabled":false,"initialOwner":1},{"index":118,"settingsHash":612402065,"planetNameId32":0,"position":{"x":0.12954043,"y":0.52342516},"waypoints":[],"sector":36,"maxHealth":1000000,"disabled":false,"initialOwner":1},{"index":119,"settingsHash":248400433,"planetNameId32":0,"position":{"x":0.033894707,"y":0.5456473},"waypoints":[],"sector":36,"maxHealth":1000000,"disabled":false,"initialOwner":1},{"index":120,"settingsHash":1423930789,"planetNameId32":0,"position":{"x":0.1969427,"y":0.5865483},"waypoints":[],"sector":36,"maxHealth":1000000,"disabled":false,"initialOwner":1},{"index":121,"settingsHash":429955586,"planetNameId32":0,"position":{"x":0.28023794,"y":0.6415732},"waypoints":[],"sector":36,"maxHealth":1000000,"disabled":false,"initialOwner":1},{"index":122,"settingsHash":137703244,"planetNameId32":0,"position":{"x":0.46854144,"y":0.5513042},"waypoints":[211],"sector":37,"maxHealth":1000000,"disabled":false,"initialOwner":1},{"index":123,"settingsHash":1156965013,"planetNameId32":0,"position":{"x":0.3994094,"y":0.6009798},"waypoints":[122],"sector":37,"maxHealth":1000000,"disabled":false,"initialOwner":1},{"index":124,"settingsHash":2435651414,"planetNameId32":0,"position":{"x":0.3259798,"y":0.4174094},"waypoints":[],"sector":20,"maxHealth":1000000,"disabled":false,"initialOwner":1},{"index":125,"settingsHash":2875368439,"planetNameId32":0,"position":{"x":0.46994886,"y":0.27418607},"waypoints":[],"sector":20,"maxHealth":2000000,"disabled":false,"initialOwner":2},{"index":126,"settingsHash":2706883571,"planetNameId32":0,"position":{"x":0.5348745,"y":0.11823793},"waypoints":[129],"sector":21,"maxHealth":2000000,"disabled":false,"initialOwner":2},{"index":127,"settingsHash":2003553249,"planetNameId32":0,"position":{"x":0.4448446,"y":0.1618837},"waypoints":[],"sector":21,"maxHealth":1000000,"disabled":false,"initialOwner":2},{"index":128,"settingsHash":2658926073,"planetNameId32":0,"position":{"x":0.6416474,"y":-0.034105327},"waypoints":[129],"sector":22,"maxHealth":1400000,"disabled":false,"initialOwner":1},{"index":129,"settingsHash":1231076923,"planetNameId32":0,"position":{"x":0.6244252,"y":0.10954041},"waypoints":[126,171,214],"sector":39,"maxHealth":1500000,"disabled":false,"initialOwner":1},{"index":130,"settingsHash":984145086,"planetNameId32":0,"position":{"x":0.6394251,"y":-0.11354046},"waypoints":[82,128],"sector":23,"maxHealth":2000000,"disabled":false,"initialOwner":1},{"index":131,"settingsHash":3921453955,"planetNameId32":0,"position":{"x":0.5706473,"y":-0.035894755},"waypoints":[126,128],"sector":23,"maxHealth":2000000,"disabled":false,"initialOwner":1},{"index":132,"settingsHash":3215655918,"planetNameId32":0,"position":{"x":0.4985732,"y":-0.21423799},"waypoints":[],"sector":24,"maxHealth":1000000,"disabled":false,"initialOwner":1},{"index":133,"settingsHash":997215371,"planetNameId32":0,"position":{"x":0.5715483,"y":-0.19894274},"waypoints":[],"sector":24,"maxHealth":1000000,"disabled":false,"initialOwner":1},{"index":134,"settingsHash":2282459618,"planetNameId32":0,"position":{"x":0.39494884,"y":-0.34418607},"waypoints":[],"sector":11,"maxHealth":1000000,"disabled":false,"initialOwner":1},{"index":135,"settingsHash":1937725917,"planetNameId32":0,"position":{"x":0.3655414,"y":-0.40630427},"waypoints":[89,136],"sector":11,"maxHealth":1500000,"disabled":false,"initialOwner":1},{"index":136,"settingsHash":3715077297,"planetNameId32":0,"position":{"x":0.30818605,"y":-0.4349489},"waypoints":[7,90,137],"sector":11,"maxHealth":1000000,"disabled":false,"initialOwner":1},{"index":137,"settingsHash":4017257734,"planetNameId32":0,"position":{"x":0.21723792,"y":-0.49157324},"waypoints":[93,180],"sector":26,"maxHealth":1000000,"disabled":false,"initialOwner":1},{"index":138,"settingsHash":1534729714,"planetNameId32":0,"position":{"x":0.11354035,"y":-0.5914251},"waypoints":[93,139,180],"sector":26,"maxHealth":2200000,"disabled":false,"initialOwner":1},{"index":139,"settingsHash":3213455987,"planetNameId32":0,"position":{"x":0.06359941,"y":-0.5271288},"waypoints":[93],"sector":26,"maxHealth":2300000,"disabled":false,"initialOwner":1},{"index":140,"settingsHash":2830340410,"planetNameId32":0,"position":{"x":-0.03489475,"y":-0.54864734},"waypoints":[],"sector":27,"maxHealth":1800000,"disabled":false,"initialOwner":1},{"index":141,"settingsHash":1297056046,"planetNameId32":0,"position":{"x":-0.12159955,"y":-0.5161287},"waypoints":[140,142,185],"sector":27,"maxHealth":2200000,"disabled":false,"initialOwner":1},{"index":142,"settingsHash":1526977116,"planetNameId32":0,"position":{"x":-0.20094277,"y":-0.4955483},"waypoints":[],"sector":27,"maxHealth":1600000,"disabled":false,"initialOwner":1},{"index":143,"settingsHash":770159872,"planetNameId32":0,"position":{"x":-0.23688374,"y":-0.5768446},"waypoints":[142,186],"sector":27,"maxHealth":1800000,"disabled":false,"initialOwner":1},{"index":144,"settingsHash":232742202,"planetNameId32":0,"position":{"x":-0.30640945,"y":-0.4626785},"waypoints":[187],"sector":28,"maxHealth":1000000,"disabled":false,"initialOwner":1},{"index":145,"settingsHash":784275392,"planetNameId32":0,"position":{"x":-0.3871862,"y":-0.43394879},"waypoints":[99,187],"sector":28,"maxHealth":1000000,"disabled":false,"initialOwner":1},{"index":146,"settingsHash":1986037000,"planetNameId32":0,"position":{"x":-0.47797978,"y":-0.3174094},"waypoints":[147],"sector":29,"maxHealth":1000000,"disabled":false,"initialOwner":1},{"index":147,"settingsHash":2935376141,"planetNameId32":0,"position":{"x":-0.4116785,"y":-0.3474094},"waypoints":[189],"sector":29,"maxHealth":1000000,"disabled":false,"initialOwner":1},{"index":148,"settingsHash":3228999359,"planetNameId32":0,"position":{"x":-0.5268447,"y":-0.18688355},"waypoints":[149],"sector":29,"maxHealth":1000000,"disabled":false,"initialOwner":1},{"index":149,"settingsHash":3482441182,"planetNameId32":0,"position":{"x":-0.47057328,"y":-0.23023784},"waypoints":[102,146],"sector":29,"maxHealth":1000000,"disabled":false,"initialOwner":1},{"index":150,"settingsHash":3480296110,"planetNameId32":0,"position":{"x":-0.5226474,"y":-0.035894625},"waypoints":[109,151,192],"sector":16,"maxHealth":2200000,"disabled":false,"initialOwner":1},{"index":151,"settingsHash":1043181,"planetNameId32":0,"position":{"x":-0.56242514,"y":-0.11354032},"waypoints":[],"sector":16,"maxHealth":1000000,"disabled":false,"initialOwner":1},{"index":152,"settingsHash":572242261,"planetNameId32":0,"position":{"x":-0.9146473,"y":-0.17310524},"waypoints":[],"sector":31,"maxHealth":1000000,"disabled":false,"initialOwner":3},{"index":153,"settingsHash":1192040123,"planetNameId32":0,"position":{"x":-0.745425,"y":-0.1314594},"waypoints":[239],"sector":31,"maxHealth":1800000,"disabled":false,"initialOwner":1},{"index":154,"settingsHash":457558822,"planetNameId32":0,"position":{"x":-0.6788745,"y":0.117238},"waypoints":[107,155],"sector":31,"maxHealth":1400000,"disabled":false,"initialOwner":1},{"index":155,"settingsHash":2655630774,"planetNameId32":0,"position":{"x":-0.73154825,"y":0.05294286},"waypoints":[197],"sector":31,"maxHealth":1800000,"disabled":false,"initialOwner":1},{"index":156,"settingsHash":3531149629,"planetNameId32":0,"position":{"x":-0.6009798,"y":0.2024094},"waypoints":[72,154,158],"sector":33,"maxHealth":1000000,"disabled":false,"initialOwner":1},{"index":157,"settingsHash":2007360508,"planetNameId32":0,"position":{"x":-0.575186,"y":0.26594892},"waypoints":[110,156,158,199],"sector":32,"maxHealth":1000000,"disabled":false,"initialOwner":1},{"index":158,"settingsHash":2564387350,"planetNameId32":0,"position":{"x":-0.7044093,"y":0.25667855},"waypoints":[242,244],"sector":32,"maxHealth":2200000,"disabled":false,"initialOwner":1},{"index":159,"settingsHash":1159313659,"planetNameId32":0,"position":{"x":-0.3992379,"y":0.5128745},"waypoints":[160,203],"sector":34,"maxHealth":1000000,"disabled":false,"initialOwner":1},{"index":160,"settingsHash":2695598028,"planetNameId32":0,"position":{"x":-0.3412379,"y":0.5515733},"waypoints":[114,204],"sector":34,"maxHealth":1000000,"disabled":false,"initialOwner":1},{"index":161,"settingsHash":1109752394,"planetNameId32":0,"position":{"x":-0.04959929,"y":0.5291288},"waypoints":[69,162],"sector":35,"maxHealth":2200000,"disabled":false,"initialOwner":1},{"index":162,"settingsHash":4171074231,"planetNameId32":0,"position":{"x":-0.07354023,"y":0.6374251},"waypoints":[163],"sector":35,"maxHealth":1700000,"disabled":false,"initialOwner":1},{"index":163,"settingsHash":1270268663,"planetNameId32":0,"position":{"x":0.061421014,"y":0.6512196},"waypoints":[],"sector":35,"maxHealth":1000000,"disabled":false,"initialOwner":1},{"index":164,"settingsHash":575825411,"planetNameId32":0,"position":{"x":0.09195879,"y":0.7373349},"waypoints":[],"sector":36,"maxHealth":1000000,"disabled":false,"initialOwner":1},{"index":165,"settingsHash":3031668844,"planetNameId32":0,"position":{"x":0.2163721,"y":0.7093697},"waypoints":[],"sector":36,"maxHealth":1000000,"disabled":false,"initialOwner":1},{"index":166,"settingsHash":3692735566,"planetNameId32":0,"position":{"x":0.47584745,"y":0.6789487},"waypoints":[167,256],"sector":37,"maxHealth":1000000,"disabled":false,"initialOwner":2},{"index":167,"settingsHash":3517952761,"planetNameId32":0,"position":{"x":0.5693348,"y":0.6043272},"waypoints":[257],"sector":37,"maxHealth":1000000,"disabled":false,"initialOwner":2},{"index":168,"settingsHash":3604506896,"planetNameId32":0,"position":{"x":0.4243272,"y":0.34833485},"waypoints":[34,124,211],"sector":38,"maxHealth":1500000,"disabled":false,"initialOwner":2},{"index":169,"settingsHash":356540875,"planetNameId32":0,"position":{"x":0.5803697,"y":0.29137206},"waypoints":[170],"sector":21,"maxHealth":1000000,"disabled":false,"initialOwner":2},{"index":170,"settingsHash":3087050848,"planetNameId32":0,"position":{"x":0.6880386,"y":0.30101782},"waypoints":[171,212],"sector":21,"maxHealth":1000000,"disabled":false,"initialOwner":2},{"index":171,"settingsHash":2036924050,"planetNameId32":0,"position":{"x":0.7302936,"y":0.14800768},"waypoints":[214],"sector":39,"maxHealth":1000000,"disabled":false,"initialOwner":1},{"index":172,"settingsHash":2254239637,"planetNameId32":0,"position":{"x":0.7312195,"y":-0.12242107},"waypoints":[130,173,175],"sector":39,"maxHealth":1000000,"disabled":false,"initialOwner":1},{"index":173,"settingsHash":1039531899,"planetNameId32":0,"position":{"x":0.8252936,"y":-0.13200772},"waypoints":[217,218],"sector":39,"maxHealth":1500000,"disabled":false,"initialOwner":1},{"index":174,"settingsHash":1730968584,"planetNameId32":0,"position":{"x":0.5600685,"y":-0.27437216},"waypoints":[],"sector":24,"maxHealth":1000000,"disabled":false,"initialOwner":1},{"index":175,"settingsHash":3461540330,"planetNameId32":0,"position":{"x":0.6873349,"y":-0.2439588},"waypoints":[218,219],"sector":24,"maxHealth":1000000,"disabled":false,"initialOwner":1},{"index":176,"settingsHash":3671746797,"planetNameId32":0,"position":{"x":0.51897186,"y":-0.3859795},"waypoints":[],"sector":25,"maxHealth":1000000,"disabled":false,"initialOwner":1},{"index":177,"settingsHash":1969390828,"planetNameId32":0,"position":{"x":0.5813272,"y":-0.45833483},"waypoints":[],"sector":25,"maxHealth":1000000,"disabled":false,"initialOwner":1},{"index":178,"settingsHash":3856827013,"planetNameId32":0,"position":{"x":0.45897943,"y":-0.45897192},"waypoints":[135],"sector":25,"maxHealth":1000000,"disabled":false,"initialOwner":1},{"index":179,"settingsHash":386932878,"planetNameId32":0,"position":{"x":0.4808474,"y":-0.5826475},"waypoints":[],"sector":25,"maxHealth":1000000,"disabled":false,"initialOwner":1},{"index":180,"settingsHash":2517847560,"planetNameId32":0,"position":{"x":0.27001774,"y":-0.5880387},"waypoints":[7,183],"sector":25,"maxHealth":1800000,"disabled":false,"initialOwner":1},{"index":181,"settingsHash":1581052380,"planetNameId32":0,"position":{"x":0.3589587,"y":-0.73933494},"waypoints":[224],"sector":25,"maxHealth":1000000,"disabled":false,"initialOwner":1},{"index":182,"settingsHash":4182360890,"planetNameId32":0,"position":{"x":0.04742095,"y":-0.64221954},"waypoints":[138,226],"sector":26,"maxHealth":1800000,"disabled":false,"initialOwner":1},{"index":183,"settingsHash":2078192573,"planetNameId32":0,"position":{"x":0.2510076,"y":-0.69129366},"waypoints":[181,224],"sector":26,"maxHealth":2200000,"disabled":false,"initialOwner":1},{"index":184,"settingsHash":1722929190,"planetNameId32":0,"position":{"x":-0.04842106,"y":-0.70721954},"waypoints":[140,182,185],"sector":43,"maxHealth":1400000,"disabled":false,"initialOwner":1},{"index":185,"settingsHash":101839064,"planetNameId32":0,"position":{"x":-0.1330078,"y":-0.6602936},"waypoints":[],"sector":43,"maxHealth":1400000,"disabled":false,"initialOwner":1},{"index":186,"settingsHash":2563880739,"planetNameId32":0,"position":{"x":-0.2649589,"y":-0.6723349},"waypoints":[185,230],"sector":27,"maxHealth":1000000,"disabled":false,"initialOwner":1},{"index":187,"settingsHash":1697634205,"planetNameId32":0,"position":{"x":-0.37284753,"y":-0.5306474},"waypoints":[143,233],"sector":28,"maxHealth":1000000,"disabled":false,"initialOwner":1},{"index":188,"settingsHash":1366049074,"planetNameId32":0,"position":{"x":-0.5559487,"y":-0.31584743},"waypoints":[146,189],"sector":30,"maxHealth":1000000,"disabled":false,"initialOwner":1},{"index":189,"settingsHash":4234355218,"planetNameId32":0,"position":{"x":-0.4953272,"y":-0.4213348},"waypoints":[145,234],"sector":30,"maxHealth":1000000,"disabled":false,"initialOwner":1},{"index":190,"settingsHash":2097290850,"planetNameId32":0,"position":{"x":-0.6140685,"y":-0.20337197},"waypoints":[148],"sector":30,"maxHealth":1000000,"disabled":false,"initialOwner":1},{"index":191,"settingsHash":3764590020,"planetNameId32":0,"position":{"x":0.03396134,"y":0.9259823},"waypoints":[],"sector":30,"maxHealth":1000000,"disabled":false,"initialOwner":1},{"index":192,"settingsHash":3052439858,"planetNameId32":0,"position":{"x":-0.62221956,"y":-0.042420916},"waypoints":[107,239],"sector":16,"maxHealth":1000000,"disabled":false,"initialOwner":1},{"index":193,"settingsHash":2845725342,"planetNameId32":0,"position":{"x":-0.6862936,"y":-0.25600755},"waypoints":[188,190,236],"sector":16,"maxHealth":1000000,"disabled":false,"initialOwner":1},{"index":194,"settingsHash":3837447591,"planetNameId32":0,"position":{"x":-0.22899726,"y":0.49906695},"waypoints":[116,117,160],"sector":46,"maxHealth":1000000,"disabled":false,"initialOwner":1},{"index":195,"settingsHash":1126502547,"planetNameId32":0,"position":{"x":-0.9272936,"y":-0.04299212},"waypoints":[196,243],"sector":46,"maxHealth":1000000,"disabled":false,"initialOwner":3},{"index":196,"settingsHash":3244992775,"planetNameId32":0,"position":{"x":-0.8473348,"y":-0.096041},"waypoints":[152,153],"sector":33,"maxHealth":1400000,"disabled":false,"initialOwner":3},{"index":197,"settingsHash":1806559160,"planetNameId32":0,"position":{"x":-0.74603856,"y":-0.03198197},"waypoints":[107,153,196],"sector":33,"maxHealth":1000000,"disabled":false,"initialOwner":1},{"index":198,"settingsHash":2831860380,"planetNameId32":0,"position":{"x":-0.43697178,"y":0.3259796},"waypoints":[110,113,199,200],"sector":33,"maxHealth":1000000,"disabled":false,"initialOwner":1},{"index":199,"settingsHash":2016899055,"planetNameId32":0,"position":{"x":-0.5379487,"y":0.3338475},"waypoints":[],"sector":33,"maxHealth":1500000,"disabled":false,"initialOwner":1},{"index":200,"settingsHash":2071495162,"planetNameId32":0,"position":{"x":-0.4909794,"y":0.4139719},"waypoints":[159,199,201],"sector":34,"maxHealth":1800000,"disabled":false,"initialOwner":1},{"index":201,"settingsHash":996779072,"planetNameId32":0,"position":{"x":-0.5683347,"y":0.4903273},"waypoints":[245,249],"sector":34,"maxHealth":1000000,"disabled":false,"initialOwner":1},{"index":202,"settingsHash":1982461871,"planetNameId32":0,"position":{"x":-0.53437203,"y":0.6510685},"waypoints":[114,260],"sector":34,"maxHealth":1000000,"disabled":false,"initialOwner":1},{"index":203,"settingsHash":3161413384,"planetNameId32":0,"position":{"x":-0.31501773,"y":0.4560387},"waypoints":[112,160,194],"sector":34,"maxHealth":1000000,"disabled":false,"initialOwner":1},{"index":204,"settingsHash":964201429,"planetNameId32":0,"position":{"x":-0.35206652,"y":0.64499736},"waypoints":[],"sector":35,"maxHealth":1000000,"disabled":false,"initialOwner":1},{"index":205,"settingsHash":319528443,"planetNameId32":0,"position":{"x":-0.32600746,"y":0.7472937},"waypoints":[204],"sector":35,"maxHealth":1000000,"disabled":false,"initialOwner":1},{"index":206,"settingsHash":1805868079,"planetNameId32":0,"position":{"x":0.084947325,"y":0.8337918},"waypoints":[],"sector":36,"maxHealth":1000000,"disabled":false,"initialOwner":1},{"index":207,"settingsHash":2174989502,"planetNameId32":0,"position":{"x":-0.06005267,"y":0.84179187},"waypoints":[251],"sector":36,"maxHealth":1300000,"disabled":false,"initialOwner":1},{"index":208,"settingsHash":1125831687,"planetNameId32":0,"position":{"x":0.3105063,"y":0.77156365},"waypoints":[],"sector":36,"maxHealth":1000000,"disabled":false,"initialOwner":1},{"index":209,"settingsHash":2595930801,"planetNameId32":0,"position":{"x":0.7657729,"y":0.5369948},"waypoints":[210],"sector":37,"maxHealth":1000000,"disabled":false,"initialOwner":2},{"index":210,"settingsHash":1644011282,"planetNameId32":0,"position":{"x":0.77812827,"y":0.3443502},"waypoints":[],"sector":37,"maxHealth":1000000,"disabled":false,"initialOwner":2},{"index":211,"settingsHash":301092871,"planetNameId32":0,"position":{"x":0.4889177,"y":0.43328553},"waypoints":[75,122],"sector":38,"maxHealth":1000000,"disabled":false,"initialOwner":2},{"index":212,"settingsHash":1344035939,"planetNameId32":0,"position":{"x":0.633865,"y":0.3955063},"waypoints":[],"sector":38,"maxHealth":1000000,"disabled":false,"initialOwner":2},{"index":213,"settingsHash":2798506372,"planetNameId32":0,"position":{"x":0.9115288,"y":0.18509296},"waypoints":[],"sector":38,"maxHealth":1000000,"disabled":false,"initialOwner":2},{"index":214,"settingsHash":2529588949,"planetNameId32":0,"position":{"x":0.7147919,"y":0.06394728},"waypoints":[217],"sector":39,"maxHealth":1000000,"disabled":false,"initialOwner":1},{"index":215,"settingsHash":2633633039,"planetNameId32":0,"position":{"x":0.8417918,"y":0.10094728},"waypoints":[171,213,217],"sector":39,"maxHealth":1000000,"disabled":false,"initialOwner":2},{"index":216,"settingsHash":3575106066,"planetNameId32":0,"position":{"x":0.93316215,"y":0.004525},"waypoints":[215],"sector":39,"maxHealth":1300000,"disabled":false,"initialOwner":2},{"index":217,"settingsHash":1050117740,"planetNameId32":0,"position":{"x":0.7587918,"y":-0.019947395},"waypoints":[128,172],"sector":39,"maxHealth":2200000,"disabled":false,"initialOwner":1},{"index":218,"settingsHash":1272337220,"planetNameId32":0,"position":{"x":0.8658252,"y":-0.30003393},"waypoints":[219],"sector":40,"maxHealth":1000000,"disabled":false,"initialOwner":1},{"index":219,"settingsHash":1029706994,"planetNameId32":0,"position":{"x":0.7575288,"y":-0.351093},"waypoints":[220],"sector":40,"maxHealth":2000000,"disabled":false,"initialOwner":1},{"index":220,"settingsHash":4039961663,"planetNameId32":0,"position":{"x":0.7659177,"y":-0.48228556},"waypoints":[221],"sector":41,"maxHealth":1000000,"disabled":false,"initialOwner":1},{"index":221,"settingsHash":3290149632,"planetNameId32":0,"position":{"x":0.66399485,"y":-0.5727729},"waypoints":[],"sector":41,"maxHealth":1000000,"disabled":false,"initialOwner":1},{"index":222,"settingsHash":3795087598,"planetNameId32":0,"position":{"x":0.58777285,"y":-0.676995},"waypoints":[],"sector":41,"maxHealth":1000000,"disabled":false,"initialOwner":1},{"index":223,"settingsHash":4053031948,"planetNameId32":0,"position":{"x":0.49028546,"y":-0.71661645},"waypoints":[],"sector":41,"maxHealth":1000000,"disabled":false,"initialOwner":1},{"index":224,"settingsHash":3659425534,"planetNameId32":0,"position":{"x":0.29350623,"y":-0.8715637},"waypoints":[181,225],"sector":42,"maxHealth":1000000,"disabled":false,"initialOwner":1},{"index":225,"settingsHash":433678065,"planetNameId32":0,"position":{"x":0.14809287,"y":-0.91152894},"waypoints":[227],"sector":42,"maxHealth":1000000,"disabled":false,"initialOwner":1},{"index":226,"settingsHash":1377257553,"planetNameId32":0,"position":{"x":0.09694725,"y":-0.7277918},"waypoints":[183,227],"sector":42,"maxHealth":1200000,"disabled":false,"initialOwner":1},{"index":227,"settingsHash":264536752,"planetNameId32":0,"position":{"x":0.104947254,"y":-0.82979184},"waypoints":[228],"sector":42,"maxHealth":1000000,"disabled":false,"initialOwner":1},{"index":228,"settingsHash":3709894755,"planetNameId32":0,"position":{"x":-0.037947383,"y":-0.8437918},"waypoints":[184,229],"sector":43,"maxHealth":1300000,"disabled":false,"initialOwner":1},{"index":229,"settingsHash":449319042,"planetNameId32":0,"position":{"x":-0.16047508,"y":-0.85416216},"waypoints":[184,230],"sector":43,"maxHealth":1000000,"disabled":false,"initialOwner":1},{"index":230,"settingsHash":1531805760,"planetNameId32":0,"position":{"x":-0.31250626,"y":-0.83086497},"waypoints":[],"sector":27,"maxHealth":1400000,"disabled":false,"initialOwner":1},{"index":231,"settingsHash":3472221087,"planetNameId32":0,"position":{"x":-0.44250628,"y":-0.76256365},"waypoints":[230],"sector":27,"maxHealth":1000000,"disabled":false,"initialOwner":1},{"index":232,"settingsHash":31903659,"planetNameId32":0,"position":{"x":-0.5732856,"y":-0.6689176},"waypoints":[231],"sector":44,"maxHealth":1000000,"disabled":false,"initialOwner":1},{"index":233,"settingsHash":728004013,"planetNameId32":0,"position":{"x":-0.48777303,"y":-0.5639948},"waypoints":[231,232],"sector":44,"maxHealth":1000000,"disabled":false,"initialOwner":1},{"index":234,"settingsHash":33972203,"planetNameId32":0,"position":{"x":-0.6169949,"y":-0.5607729},"waypoints":[232],"sector":45,"maxHealth":1000000,"disabled":false,"initialOwner":1},{"index":235,"settingsHash":3339959103,"planetNameId32":0,"position":{"x":-0.75561637,"y":-0.5062855},"waypoints":[234,236],"sector":45,"maxHealth":1000000,"disabled":false,"initialOwner":1},{"index":236,"settingsHash":3478070727,"planetNameId32":0,"position":{"x":-0.6258253,"y":-0.40203378},"waypoints":[],"sector":45,"maxHealth":1000000,"disabled":false,"initialOwner":1},{"index":237,"settingsHash":1923795699,"planetNameId32":0,"position":{"x":-0.8608651,"y":-0.36050615},"waypoints":[235],"sector":45,"maxHealth":1000000,"disabled":false,"initialOwner":1},{"index":238,"settingsHash":2658611086,"planetNameId32":0,"position":{"x":-0.7807918,"y":-0.3289472},"waypoints":[241],"sector":46,"maxHealth":1000000,"disabled":false,"initialOwner":3},{"index":239,"settingsHash":2659689769,"planetNameId32":0,"position":{"x":-0.6268659,"y":-0.12653387},"waypoints":[151],"sector":46,"maxHealth":2200000,"disabled":false,"initialOwner":1},{"index":240,"settingsHash":1049999007,"planetNameId32":0,"position":{"x":-0.9021621,"y":0.15547518},"waypoints":[243],"sector":46,"maxHealth":1000000,"disabled":false,"initialOwner":1},{"index":241,"settingsHash":2216912817,"planetNameId32":0,"position":{"x":-0.8157918,"y":-0.2170526},"waypoints":[152,153],"sector":46,"maxHealth":1600000,"disabled":false,"initialOwner":3},{"index":242,"settingsHash":260933067,"planetNameId32":0,"position":{"x":-0.806865,"y":0.20750636},"waypoints":[240,243],"sector":48,"maxHealth":1000000,"disabled":false,"initialOwner":1},{"index":243,"settingsHash":230950549,"planetNameId32":0,"position":{"x":-0.840825,"y":0.06103413},"waypoints":[155,197],"sector":48,"maxHealth":1000000,"disabled":false,"initialOwner":1},{"index":244,"settingsHash":17046409,"planetNameId32":0,"position":{"x":-0.74635,"y":0.3441284},"waypoints":[242,247],"sector":49,"maxHealth":1400000,"disabled":false,"initialOwner":1},{"index":245,"settingsHash":3825459240,"planetNameId32":0,"position":{"x":-0.6519177,"y":0.45428553},"waypoints":[],"sector":49,"maxHealth":2000000,"disabled":false,"initialOwner":1},{"index":246,"settingsHash":229350423,"planetNameId32":0,"position":{"x":-0.7952854,"y":0.4969178},"waypoints":[245,247,249],"sector":50,"maxHealth":1500000,"disabled":false,"initialOwner":1},{"index":247,"settingsHash":1554138344,"planetNameId32":0,"position":{"x":-0.8741281,"y":0.3473503},"waypoints":[],"sector":50,"maxHealth":1000000,"disabled":false,"initialOwner":1},{"index":248,"settingsHash":1826401325,"planetNameId32":0,"position":{"x":-0.56103384,"y":0.77082515},"waypoints":[202],"sector":50,"maxHealth":1000000,"disabled":false,"initialOwner":1},{"index":249,"settingsHash":2165203458,"planetNameId32":0,"position":{"x":-0.6895062,"y":0.5908651},"waypoints":[245],"sector":50,"maxHealth":1000000,"disabled":false,"initialOwner":1},{"index":250,"settingsHash":714233297,"planetNameId32":0,"position":{"x":-0.13953374,"y":0.7098659},"waypoints":[70,162,251],"sector":35,"maxHealth":1000000,"disabled":false,"initialOwner":1},{"index":251,"settingsHash":252504470,"planetNameId32":0,"position":{"x":-0.048947096,"y":0.72179186},"waypoints":[162],"sector":35,"maxHealth":1000000,"disabled":false,"initialOwner":1},{"index":252,"settingsHash":2360232252,"planetNameId32":0,"position":{"x":-0.35552636,"y":0.8833641},"waypoints":[253],"sector":51,"maxHealth":1000000,"disabled":false,"initialOwner":1},{"index":253,"settingsHash":1524642040,"planetNameId32":0,"position":{"x":-0.19952635,"y":0.9263641},"waypoints":[207],"sector":51,"maxHealth":1000000,"disabled":false,"initialOwner":1},{"index":254,"settingsHash":3789806846,"planetNameId32":0,"position":{"x":0.14810903,"y":0.9233154},"waypoints":[],"sector":52,"maxHealth":1000000,"disabled":false,"initialOwner":1},{"index":255,"settingsHash":3809134104,"planetNameId32":0,"position":{"x":0.3191681,"y":0.8730191},"waypoints":[],"sector":52,"maxHealth":1000000,"disabled":false,"initialOwner":1},{"index":256,"settingsHash":4020204519,"planetNameId32":0,"position":{"x":0.5267236,"y":0.7475853},"waypoints":[257],"sector":53,"maxHealth":1000000,"disabled":false,"initialOwner":2},{"index":257,"settingsHash":1588671273,"planetNameId32":0,"position":{"x":0.6665664,"y":0.6070179},"waypoints":[209],"sector":53,"maxHealth":1000000,"disabled":false,"initialOwner":2},{"index":258,"settingsHash":843081973,"planetNameId32":0,"position":{"x":0.55758536,"y":0.4887236},"waypoints":[211],"sector":53,"maxHealth":2000000,"disabled":false,"initialOwner":2},{"index":259,"settingsHash":3966660905,"planetNameId32":0,"position":{"x":0.6838866,"y":0.48672357},"waypoints":[212,258],"sector":53,"maxHealth":3000000,"disabled":false,"initialOwner":2},{"index":260,"settingsHash":3923589145,"planetNameId32":0,"position":{"x":-0.438396,"y":0.6977152},"waypoints":[205],"sector":49,"maxHealth":15000000,"disabled":false,"initialOwner":1},{"index":261,"settingsHash":3487417548,"planetNameId32":1441504339,"position":{"x":-0.729,"y":0.172},"waypoints":[154,158,242],"sector":0,"maxHealth":2000000,"disabled":false,"initialOwner":1},{"index":262,"settingsHash":1143730827,"planetNameId32":1441504339,"position":{"x":-0.657,"y":0.33},"waypoints":[158,244],"sector":0,"maxHealth":2000000,"disabled":false,"initialOwner":1},{"index":263,"settingsHash":666353454,"planetNameId32":1441504339,"position":{"x":0,"y":0},"waypoints":[],"sector":0,"maxHealth":2000000,"disabled":false,"initialOwner":1},{"index":264,"settingsHash":3117259984,"planetNameId32":1441504339,"position":{"x":0,"y":0},"waypoints":[],"sector":0,"maxHealth":2000000,"disabled":false,"initialOwner":1},{"index":265,"settingsHash":3060137094,"planetNameId32":1441504339,"position":{"x":0,"y":0},"waypoints":[],"sector":0,"maxHealth":2000000,"disabled":false,"initialOwner":1},{"index":266,"settingsHash":1316898847,"planetNameId32":1441504339,"position":{"x":-0.766,"y":0.41},"waypoints":[244,246],"sector":0,"maxHealth":2000000,"disabled":false,"initialOwner":1}],"homeWorlds":[{"race":1,"planetIndices":[0]},{"race":3,"planetIndices":[260]}],"capitalInfos":[],"planetPermanentEffects":[],"planetRegions":[{"planetIndex":0,"regionIndex":0,"settingsHash":4196558004,"maxHealth":600000,"regionSize":3,"flags":0,"damageMultiplier":1.5},{"planetIndex":0,"regionIndex":1,"settingsHash":3958784315,"maxHealth":600000,"regionSize":3,"flags":0,"damageMultiplier":1.5},{"planetIndex":0,"regionIndex":2,"settingsHash":1199462527,"maxHealth":600000,"regionSize":3,"flags":0,"damageMultiplier":1.5},{"planetIndex":0,"regionIndex":3,"settingsHash":391918492,"maxHealth":600000,"regionSize":3,"flags":0,"damageMultiplier":1.5},{"planetIndex":0,"regionIndex":4,"settingsHash":502504685,"maxHealth":600000,"regionSize":3,"flags":0,"damageMultiplier":1.5},{"planetIndex":0,"regionIndex":5,"settingsHash":1750980320,"maxHealth":600000,"regionSize":3,"flags":0,"damageMultiplier":1.5},{"planetIndex":0,"regionIndex":6,"settingsHash":550918906,"maxHealth":600000,"regionSize":3,"flags":0,"damageMultiplier":1.5},{"planetIndex":7,"regionIndex":0,"settingsHash":3455315905,"maxHealth":200000,"regionSize":1,"flags":0,"damageMultiplier":1.5},{"planetIndex":7,"regionIndex":1,"settingsHash":518148662,"maxHealth":100000,"regionSize":0,"flags":0,"damageMultiplier":1.5},{"planetIndex":7,"regionIndex":2,"settingsHash":2775422932,"maxHealth":400000,"regionSize":2,"flags":0,"damageMultiplier":1.5},{"planetIndex":16,"regionIndex":0,"settingsHash":2557369266,"maxHealth":200000,"regionSize":1,"flags":0,"damageMultiplier":1.5},{"planetIndex":16,"regionIndex":1,"settingsHash":3540948886,"maxHealth":400000,"regionSize":2,"flags":0,"damageMultiplier":1.5},{"planetIndex":16,"regionIndex":2,"settingsHash":991650372,"maxHealth":200000,"regionSize":1,"flags":0,"damageMultiplier":1.5},{"planetIndex":16,"regionIndex":3,"settingsHash":1239520232,"maxHealth":600000,"regionSize":3,"flags":0,"damageMultiplier":1.5},{"planetIndex":28,"regionIndex":0,"settingsHash":1954453569,"maxHealth":200000,"regionSize":1,"flags":0,"damageMultiplier":1.5},{"planetIndex":28,"regionIndex":1,"settingsHash":1451291824,"maxHealth":200000,"regionSize":1,"flags":0,"damageMultiplier":1.5},{"planetIndex":28,"regionIndex":2,"settingsHash":311758306,"maxHealth":600000,"regionSize":3,"flags":0,"damageMultiplier":1.5},{"planetIndex":29,"regionIndex":0,"settingsHash":1178227778,"maxHealth":100000,"regionSize":0,"flags":0,"damageMultiplier":1.5},{"planetIndex":29,"regionIndex":1,"settingsHash":3116199682,"maxHealth":200000,"regionSize":1,"flags":0,"damageMultiplier":1.5},{"planetIndex":29,"regionIndex":2,"settingsHash":3175334400,"maxHealth":600000,"regionSize":3,"flags":0,"damageMultiplier":1.5},{"planetIndex":29,"regionIndex":3,"settingsHash":718092071,"maxHealth":600000,"regionSize":3,"flags":0,"damageMultiplier":1.5},{"planetIndex":32,"regionIndex":0,"settingsHash":27836851,"maxHealth":600000,"regionSize":3,"flags":0,"damageMultiplier":1.5},{"planetIndex":33,"regionIndex":0,"settingsHash":3205582835,"maxHealth":200000,"regionSize":1,"flags":0,"damageMultiplier":1.5},{"planetIndex":33,"regionIndex":1,"settingsHash":1201038992,"maxHealth":100000,"regionSize":0,"flags":0,"damageMultiplier":1.5},{"planetIndex":33,"regionIndex":2,"settingsHash":334066640,"maxHealth":400000,"regionSize":2,"flags":0,"damageMultiplier":1.5},{"planetIndex":33,"regionIndex":3,"settingsHash":491224618,"maxHealth":600000,"regionSize":3,"flags":0,"damageMultiplier":1.5},{"planetIndex":36,"regionIndex":0,"settingsHash":2849889311,"maxHealth":100000,"regionSize":0,"flags":0,"damageMultiplier":1.5},{"planetIndex":36,"regionIndex":1,"settingsHash":2106184075,"maxHealth":200000,"regionSize":1,"flags":0,"damageMultiplier":1.5},{"planetIndex":36,"regionIndex":2,"settingsHash":1543050297,"maxHealth":400000,"regionSize":2,"flags":0,"damageMultiplier":1.5},{"planetIndex":37,"regionIndex":0,"settingsHash":2180989349,"maxHealth":200000,"regionSize":1,"flags":0,"damageMultiplier":1.5},{"planetIndex":37,"regionIndex":1,"settingsHash":1063822606,"maxHealth":400000,"regionSize":2,"flags":0,"damageMultiplier":1.5},{"planetIndex":37,"regionIndex":2,"settingsHash":3385219022,"maxHealth":400000,"regionSize":2,"flags":0,"damageMultiplier":1.5},{"planetIndex":42,"regionIndex":0,"settingsHash":1193052974,"maxHealth":600000,"regionSize":3,"flags":0,"damageMultiplier":1.5},{"planetIndex":44,"regionIndex":0,"settingsHash":1415969325,"maxHealth":200000,"regionSize":1,"flags":0,"damageMultiplier":1.5},{"planetIndex":44,"regionIndex":1,"settingsHash":832046850,"maxHealth":600000,"regionSize":3,"flags":0,"damageMultiplier":1.5},{"planetIndex":44,"regionIndex":2,"settingsHash":2006541056,"maxHealth":600000,"regionSize":3,"flags":0,"damageMultiplier":1.5},{"planetIndex":53,"regionIndex":0,"settingsHash":1028801816,"maxHealth":400000,"regionSize":2,"flags":0,"damageMultiplier":1.5},{"planetIndex":53,"regionIndex":1,"settingsHash":3634134154,"maxHealth":400000,"regionSize":2,"flags":0,"damageMultiplier":1.5},{"planetIndex":53,"regionIndex":2,"settingsHash":1762725992,"maxHealth":400000,"regionSize":2,"flags":0,"damageMultiplier":1.5},{"planetIndex":56,"regionIndex":0,"settingsHash":3849073717,"maxHealth":400000,"regionSize":2,"flags":0,"damageMultiplier":1.5},{"planetIndex":56,"regionIndex":1,"settingsHash":2098963156,"maxHealth":200000,"regionSize":1,"flags":0,"damageMultiplier":1.5},{"planetIndex":56,"regionIndex":2,"settingsHash":1428185423,"maxHealth":400000,"regionSize":2,"flags":0,"damageMultiplier":1.5},{"planetIndex":57,"regionIndex":0,"settingsHash":4221006651,"maxHealth":200000,"regionSize":1,"flags":0,"damageMultiplier":1.5},{"planetIndex":57,"regionIndex":1,"settingsHash":484247622,"maxHealth":200000,"regionSize":1,"flags":0,"damageMultiplier":1.5},{"planetIndex":57,"regionIndex":2,"settingsHash":3066706899,"maxHealth":600000,"regionSize":3,"flags":0,"damageMultiplier":1.5},{"planetIndex":58,"regionIndex":0,"settingsHash":511490869,"maxHealth":400000,"regionSize":2,"flags":0,"damageMultiplier":1.5},{"planetIndex":58,"regionIndex":1,"settingsHash":2491531357,"maxHealth":600000,"regionSize":3,"flags":0,"damageMultiplier":1.5},{"planetIndex":60,"regionIndex":0,"settingsHash":119875523,"maxHealth":100000,"regionSize":0,"flags":0,"damageMultiplier":1.5},{"planetIndex":60,"regionIndex":1,"settingsHash":586167831,"maxHealth":200000,"regionSize":1,"flags":0,"damageMultiplier":1.5},{"planetIndex":60,"regionIndex":2,"settingsHash":3054618608,"maxHealth":400000,"regionSize":2,"flags":0,"damageMultiplier":1.5},{"planetIndex":61,"regionIndex":0,"settingsHash":16522331,"maxHealth":200000,"regionSize":1,"flags":0,"damageMultiplier":1.5},{"planetIndex":61,"regionIndex":1,"settingsHash":167295516,"maxHealth":100000,"regionSize":0,"flags":0,"damageMultiplier":1.5},{"planetIndex":61,"regionIndex":2,"settingsHash":4275209727,"maxHealth":600000,"regionSize":3,"flags":0,"damageMultiplier":1.5},{"planetIndex":67,"regionIndex":0,"settingsHash":316170794,"maxHealth":100000,"regionSize":0,"flags":0,"damageMultiplier":1.5},{"planetIndex":67,"regionIndex":1,"settingsHash":3921926208,"maxHealth":100000,"regionSize":0,"flags":0,"damageMultiplier":1.5},{"planetIndex":67,"regionIndex":2,"settingsHash":281317935,"maxHealth":100000,"regionSize":0,"flags":0,"damageMultiplier":1.5},{"planetIndex":72,"regionIndex":0,"settingsHash":3034375188,"maxHealth":600000,"regionSize":3,"flags":0,"damageMultiplier":1.5},{"planetIndex":78,"regionIndex":0,"settingsHash":1032709433,"maxHealth":100000,"regionSize":0,"flags":0,"damageMultiplier":1.5},{"planetIndex":78,"regionIndex":1,"settingsHash":1161134727,"maxHealth":400000,"regionSize":2,"flags":0,"damageMultiplier":1.5},{"planetIndex":80,"regionIndex":0,"settingsHash":4151302370,"maxHealth":200000,"regionSize":1,"flags":0,"damageMultiplier":1.5},{"planetIndex":80,"regionIndex":1,"settingsHash":649934138,"maxHealth":600000,"regionSize":3,"flags":0,"damageMultiplier":1.5},{"planetIndex":81,"regionIndex":0,"settingsHash":1097134956,"maxHealth":200000,"regionSize":1,"flags":0,"damageMultiplier":1.5},{"planetIndex":81,"regionIndex":1,"settingsHash":1702672301,"maxHealth":100000,"regionSize":0,"flags":0,"damageMultiplier":1.5},{"planetIndex":82,"regionIndex":0,"settingsHash":770916674,"maxHealth":200000,"regionSize":1,"flags":0,"damageMultiplier":1.5},{"planetIndex":82,"regionIndex":1,"settingsHash":3147829923,"maxHealth":400000,"regionSize":2,"flags":0,"damageMultiplier":1.5},{"planetIndex":88,"regionIndex":0,"settingsHash":706797536,"maxHealth":200000,"regionSize":1,"flags":0,"damageMultiplier":1.5},{"planetIndex":88,"regionIndex":1,"settingsHash":2184145680,"maxHealth":200000,"regionSize":1,"flags":0,"damageMultiplier":1.5},{"planetIndex":88,"regionIndex":2,"settingsHash":2126832849,"maxHealth":400000,"regionSize":2,"flags":0,"damageMultiplier":1.5},{"planetIndex":90,"regionIndex":0,"settingsHash":1713282699,"maxHealth":100000,"regionSize":0,"flags":0,"damageMultiplier":1.5},{"planetIndex":90,"regionIndex":1,"settingsHash":438247765,"maxHealth":400000,"regionSize":2,"flags":0,"damageMultiplier":1.5},{"planetIndex":90,"regionIndex":2,"settingsHash":3363260441,"maxHealth":400000,"regionSize":2,"flags":0,"damageMultiplier":1.5},{"planetIndex":92,"regionIndex":0,"settingsHash":1897395642,"maxHealth":400000,"regionSize":2,"flags":0,"damageMultiplier":1.5},{"planetIndex":92,"regionIndex":1,"settingsHash":3626214155,"maxHealth":100000,"regionSize":0,"flags":0,"damageMultiplier":1.5},{"planetIndex":92,"regionIndex":2,"settingsHash":3851016682,"maxHealth":600000,"regionSize":3,"flags":0,"damageMultiplier":1.5},{"planetIndex":94,"regionIndex":0,"settingsHash":3263317504,"maxHealth":400000,"regionSize":2,"flags":0,"damageMultiplier":1.5},{"planetIndex":95,"regionIndex":0,"settingsHash":2507971325,"maxHealth":200000,"regionSize":1,"flags":0,"damageMultiplier":1.5},{"planetIndex":95,"regionIndex":1,"settingsHash":2591044773,"maxHealth":400000,"regionSize":2,"flags":0,"damageMultiplier":1.5},{"planetIndex":100,"regionIndex":0,"settingsHash":4187567384,"maxHealth":400000,"regionSize":2,"flags":0,"damageMultiplier":1.5},{"planetIndex":100,"regionIndex":1,"settingsHash":687069999,"maxHealth":100000,"regionSize":0,"flags":0,"damageMultiplier":1.5},{"planetIndex":100,"regionIndex":2,"settingsHash":1123715107,"maxHealth":400000,"regionSize":2,"flags":0,"damageMultiplier":1.5},{"planetIndex":102,"regionIndex":0,"settingsHash":2231267715,"maxHealth":100000,"regionSize":0,"flags":0,"damageMultiplier":1.5},{"planetIndex":102,"regionIndex":1,"settingsHash":1954581243,"maxHealth":400000,"regionSize":2,"flags":0,"damageMultiplier":1.5},{"planetIndex":107,"regionIndex":0,"settingsHash":2788606019,"maxHealth":200000,"regionSize":1,"flags":0,"damageMultiplier":1.5},{"planetIndex":107,"regionIndex":1,"settingsHash":539875676,"maxHealth":400000,"regionSize":2,"flags":0,"damageMultiplier":1.5},{"planetIndex":110,"regionIndex":0,"settingsHash":2143424881,"maxHealth":200000,"regionSize":1,"flags":0,"damageMultiplier":1.5},{"planetIndex":110,"regionIndex":1,"settingsHash":2895050350,"maxHealth":400000,"regionSize":2,"flags":0,"damageMultiplier":1.5},{"planetIndex":112,"regionIndex":0,"settingsHash":873382628,"maxHealth":100000,"regionSize":0,"flags":0,"damageMultiplier":1.5},{"planetIndex":112,"regionIndex":1,"settingsHash":1365889454,"maxHealth":200000,"regionSize":1,"flags":0,"damageMultiplier":1.5},{"planetIndex":112,"regionIndex":2,"settingsHash":763067932,"maxHealth":200000,"regionSize":1,"flags":0,"damageMultiplier":1.5},{"planetIndex":114,"regionIndex":0,"settingsHash":2033316867,"maxHealth":400000,"regionSize":2,"flags":0,"damageMultiplier":1.5},{"planetIndex":114,"regionIndex":1,"settingsHash":2903117961,"maxHealth":200000,"regionSize":1,"flags":0,"damageMultiplier":1.5},{"planetIndex":116,"regionIndex":0,"settingsHash":3900513024,"maxHealth":100000,"regionSize":0,"flags":0,"damageMultiplier":1.5},{"planetIndex":116,"regionIndex":1,"settingsHash":4038285524,"maxHealth":600000,"regionSize":3,"flags":0,"damageMultiplier":1.5},{"planetIndex":117,"regionIndex":0,"settingsHash":4179557814,"maxHealth":200000,"regionSize":1,"flags":0,"damageMultiplier":1.5},{"planetIndex":125,"regionIndex":0,"settingsHash":2057457464,"maxHealth":200000,"regionSize":1,"flags":0,"damageMultiplier":1.5},{"planetIndex":125,"regionIndex":1,"settingsHash":189783404,"maxHealth":200000,"regionSize":1,"flags":0,"damageMultiplier":1.5},{"planetIndex":125,"regionIndex":2,"settingsHash":3342476592,"maxHealth":600000,"regionSize":3,"flags":0,"damageMultiplier":1.5},{"planetIndex":126,"regionIndex":0,"settingsHash":3924472281,"maxHealth":400000,"regionSize":2,"flags":0,"damageMultiplier":1.5},{"planetIndex":126,"regionIndex":1,"settingsHash":3263074211,"maxHealth":200000,"regionSize":1,"flags":0,"damageMultiplier":1.5},{"planetIndex":126,"regionIndex":2,"settingsHash":3090254958,"maxHealth":400000,"regionSize":2,"flags":0,"damageMultiplier":1.5},{"planetIndex":128,"regionIndex":0,"settingsHash":1050611219,"maxHealth":400000,"regionSize":2,"flags":0,"damageMultiplier":1.5},{"planetIndex":129,"regionIndex":0,"settingsHash":324613052,"maxHealth":100000,"regionSize":0,"flags":0,"damageMultiplier":1.5},{"planetIndex":129,"regionIndex":1,"settingsHash":855833074,"maxHealth":400000,"regionSize":2,"flags":0,"damageMultiplier":1.5},{"planetIndex":130,"regionIndex":0,"settingsHash":559843220,"maxHealth":200000,"regionSize":1,"flags":0,"damageMultiplier":1.5},{"planetIndex":130,"regionIndex":1,"settingsHash":1578230839,"maxHealth":400000,"regionSize":2,"flags":0,"damageMultiplier":1.5},{"planetIndex":130,"regionIndex":2,"settingsHash":2762012044,"maxHealth":400000,"regionSize":2,"flags":0,"damageMultiplier":1.5},{"planetIndex":131,"regionIndex":0,"settingsHash":2634421583,"maxHealth":200000,"regionSize":1,"flags":0,"damageMultiplier":1.5},{"planetIndex":131,"regionIndex":1,"settingsHash":1872830438,"maxHealth":400000,"regionSize":2,"flags":0,"damageMultiplier":1.5},{"planetIndex":131,"regionIndex":2,"settingsHash":1978368732,"maxHealth":400000,"regionSize":2,"flags":0,"damageMultiplier":1.5},{"planetIndex":135,"regionIndex":0,"settingsHash":3106360883,"maxHealth":100000,"regionSize":0,"flags":0,"damageMultiplier":1.5},{"planetIndex":135,"regionIndex":1,"settingsHash":2547946895,"maxHealth":400000,"regionSize":2,"flags":0,"damageMultiplier":1.5},{"planetIndex":138,"regionIndex":0,"settingsHash":755864726,"maxHealth":200000,"regionSize":1,"flags":0,"damageMultiplier":1.5},{"planetIndex":138,"regionIndex":1,"settingsHash":2258293610,"maxHealth":200000,"regionSize":1,"flags":0,"damageMultiplier":1.5},{"planetIndex":138,"regionIndex":2,"settingsHash":3006088005,"maxHealth":200000,"regionSize":1,"flags":0,"damageMultiplier":1.5},{"planetIndex":138,"regionIndex":3,"settingsHash":476417027,"maxHealth":600000,"regionSize":3,"flags":0,"damageMultiplier":1.5},{"planetIndex":139,"regionIndex":0,"settingsHash":1023474728,"maxHealth":200000,"regionSize":1,"flags":0,"damageMultiplier":1.5},{"planetIndex":139,"regionIndex":1,"settingsHash":2696938432,"maxHealth":400000,"regionSize":2,"flags":0,"damageMultiplier":1.5},{"planetIndex":139,"regionIndex":2,"settingsHash":1344426011,"maxHealth":100000,"regionSize":0,"flags":0,"damageMultiplier":1.5},{"planetIndex":139,"regionIndex":3,"settingsHash":4127238767,"maxHealth":600000,"regionSize":3,"flags":0,"damageMultiplier":1.5},{"planetIndex":140,"regionIndex":0,"settingsHash":2876102528,"maxHealth":400000,"regionSize":2,"flags":0,"damageMultiplier":1.5},{"planetIndex":140,"regionIndex":1,"settingsHash":1143862620,"maxHealth":400000,"regionSize":2,"flags":0,"damageMultiplier":1.5},{"planetIndex":141,"regionIndex":0,"settingsHash":483548446,"maxHealth":400000,"regionSize":2,"flags":0,"damageMultiplier":1.5},{"planetIndex":141,"regionIndex":1,"settingsHash":1338066975,"maxHealth":200000,"regionSize":1,"flags":0,"damageMultiplier":1.5},{"planetIndex":141,"regionIndex":2,"settingsHash":3896987202,"maxHealth":600000,"regionSize":3,"flags":0,"damageMultiplier":1.5},{"planetIndex":142,"regionIndex":0,"settingsHash":2919580452,"maxHealth":600000,"regionSize":3,"flags":0,"damageMultiplier":1.5},{"planetIndex":143,"regionIndex":0,"settingsHash":2541292675,"maxHealth":400000,"regionSize":2,"flags":0,"damageMultiplier":1.5},{"planetIndex":143,"regionIndex":1,"settingsHash":2500124294,"maxHealth":400000,"regionSize":2,"flags":0,"damageMultiplier":1.5},{"planetIndex":150,"regionIndex":0,"settingsHash":1761215575,"maxHealth":400000,"regionSize":2,"flags":0,"damageMultiplier":1.5},{"planetIndex":150,"regionIndex":1,"settingsHash":4204734822,"maxHealth":400000,"regionSize":2,"flags":0,"damageMultiplier":1.5},{"planetIndex":150,"regionIndex":2,"settingsHash":1725242014,"maxHealth":400000,"regionSize":2,"flags":0,"damageMultiplier":1.5},{"planetIndex":153,"regionIndex":0,"settingsHash":741084747,"maxHealth":400000,"regionSize":2,"flags":0,"damageMultiplier":1.5},{"planetIndex":153,"regionIndex":1,"settingsHash":521454425,"maxHealth":400000,"regionSize":2,"flags":0,"damageMultiplier":1.5},{"planetIndex":154,"regionIndex":0,"settingsHash":2409136536,"maxHealth":400000,"regionSize":2,"flags":0,"damageMultiplier":1.5},{"planetIndex":155,"regionIndex":0,"settingsHash":3188612954,"maxHealth":100000,"regionSize":0,"flags":0,"damageMultiplier":1.5},{"planetIndex":155,"regionIndex":1,"settingsHash":1329166626,"maxHealth":100000,"regionSize":0,"flags":0,"damageMultiplier":1.5},{"planetIndex":155,"regionIndex":2,"settingsHash":1039071856,"maxHealth":600000,"regionSize":3,"flags":0,"damageMultiplier":1.5},{"planetIndex":158,"regionIndex":0,"settingsHash":4121418923,"maxHealth":200000,"regionSize":1,"flags":0,"damageMultiplier":1.5},{"planetIndex":158,"regionIndex":1,"settingsHash":400630653,"maxHealth":400000,"regionSize":2,"flags":0,"damageMultiplier":1.5},{"planetIndex":158,"regionIndex":2,"settingsHash":1017291850,"maxHealth":600000,"regionSize":3,"flags":0,"damageMultiplier":1.5},{"planetIndex":161,"regionIndex":0,"settingsHash":3028191212,"maxHealth":400000,"regionSize":2,"flags":0,"damageMultiplier":1.5},{"planetIndex":161,"regionIndex":1,"settingsHash":3841350324,"maxHealth":400000,"regionSize":2,"flags":0,"damageMultiplier":1.5},{"planetIndex":161,"regionIndex":2,"settingsHash":3647907388,"maxHealth":600000,"regionSize":3,"flags":0,"damageMultiplier":1.5},{"planetIndex":162,"regionIndex":0,"settingsHash":4051063223,"maxHealth":100000,"regionSize":0,"flags":0,"damageMultiplier":1.5},{"planetIndex":162,"regionIndex":1,"settingsHash":2332413862,"maxHealth":200000,"regionSize":1,"flags":0,"damageMultiplier":1.5},{"planetIndex":162,"regionIndex":2,"settingsHash":3568007842,"maxHealth":400000,"regionSize":2,"flags":0,"damageMultiplier":1.5},{"planetIndex":168,"regionIndex":0,"settingsHash":905823730,"maxHealth":200000,"regionSize":1,"flags":0,"damageMultiplier":1.5},{"planetIndex":168,"regionIndex":1,"settingsHash":1676064266,"maxHealth":100000,"regionSize":0,"flags":0,"damageMultiplier":1.5},{"planetIndex":168,"regionIndex":2,"settingsHash":523284406,"maxHealth":200000,"regionSize":1,"flags":0,"damageMultiplier":1.5},{"planetIndex":173,"regionIndex":0,"settingsHash":3964263469,"maxHealth":100000,"regionSize":0,"flags":0,"damageMultiplier":1.5},{"planetIndex":173,"regionIndex":1,"settingsHash":3067104866,"maxHealth":400000,"regionSize":2,"flags":0,"damageMultiplier":1.5},{"planetIndex":180,"regionIndex":0,"settingsHash":314025568,"maxHealth":200000,"regionSize":1,"flags":0,"damageMultiplier":1.5},{"planetIndex":180,"regionIndex":1,"settingsHash":2391484056,"maxHealth":200000,"regionSize":1,"flags":0,"damageMultiplier":1.5},{"planetIndex":180,"regionIndex":2,"settingsHash":3185820932,"maxHealth":400000,"regionSize":2,"flags":0,"damageMultiplier":1.5},{"planetIndex":182,"regionIndex":0,"settingsHash":472831334,"maxHealth":400000,"regionSize":2,"flags":0,"damageMultiplier":1.5},{"planetIndex":182,"regionIndex":1,"settingsHash":874781515,"maxHealth":400000,"regionSize":2,"flags":0,"damageMultiplier":1.5},{"planetIndex":183,"regionIndex":0,"settingsHash":3491570579,"maxHealth":400000,"regionSize":2,"flags":0,"damageMultiplier":1.5},{"planetIndex":183,"regionIndex":1,"settingsHash":2519594311,"maxHealth":400000,"regionSize":2,"flags":0,"damageMultiplier":1.5},{"planetIndex":183,"regionIndex":2,"settingsHash":3212629027,"maxHealth":400000,"regionSize":2,"flags":0,"damageMultiplier":1.5},{"planetIndex":184,"regionIndex":0,"settingsHash":3184875338,"maxHealth":400000,"regionSize":2,"flags":0,"damageMultiplier":1.5},{"planetIndex":185,"regionIndex":0,"settingsHash":786867005,"maxHealth":400000,"regionSize":2,"flags":0,"damageMultiplier":1.5},{"planetIndex":196,"regionIndex":0,"settingsHash":1501066740,"maxHealth":100000,"regionSize":0,"flags":0,"damageMultiplier":1.5},{"planetIndex":196,"regionIndex":1,"settingsHash":829716394,"maxHealth":100000,"regionSize":0,"flags":0,"damageMultiplier":1.5},{"planetIndex":196,"regionIndex":2,"settingsHash":4162876257,"maxHealth":200000,"regionSize":1,"flags":0,"damageMultiplier":1.5},{"planetIndex":199,"regionIndex":0,"settingsHash":3421372928,"maxHealth":100000,"regionSize":0,"flags":0,"damageMultiplier":1.5},{"planetIndex":199,"regionIndex":1,"settingsHash":4087006817,"maxHealth":400000,"regionSize":2,"flags":0,"damageMultiplier":1.5},{"planetIndex":200,"regionIndex":0,"settingsHash":1199071894,"maxHealth":400000,"regionSize":2,"flags":0,"damageMultiplier":1.5},{"planetIndex":200,"regionIndex":1,"settingsHash":2853318855,"maxHealth":200000,"regionSize":1,"flags":0,"damageMultiplier":1.5},{"planetIndex":207,"regionIndex":0,"settingsHash":3513777986,"maxHealth":100000,"regionSize":0,"flags":0,"damageMultiplier":1.5},{"planetIndex":207,"regionIndex":1,"settingsHash":3910908375,"maxHealth":200000,"regionSize":1,"flags":0,"damageMultiplier":1.5},{"planetIndex":216,"regionIndex":0,"settingsHash":2541809256,"maxHealth":100000,"regionSize":0,"flags":0,"damageMultiplier":1.5},{"planetIndex":216,"regionIndex":1,"settingsHash":3858818769,"maxHealth":200000,"regionSize":1,"flags":0,"damageMultiplier":1.5},{"planetIndex":217,"regionIndex":0,"settingsHash":2253802431,"maxHealth":200000,"regionSize":1,"flags":0,"damageMultiplier":1.5},{"planetIndex":217,"regionIndex":1,"settingsHash":481340922,"maxHealth":400000,"regionSize":2,"flags":0,"damageMultiplier":1.5},{"planetIndex":217,"regionIndex":2,"settingsHash":1121037205,"maxHealth":600000,"regionSize":3,"flags":0,"damageMultiplier":1.5},{"planetIndex":219,"regionIndex":0,"settingsHash":3550784979,"maxHealth":400000,"regionSize":2,"flags":0,"damageMultiplier":1.5},{"planetIndex":219,"regionIndex":1,"settingsHash":974467043,"maxHealth":200000,"regionSize":1,"flags":0,"damageMultiplier":1.5},{"planetIndex":219,"regionIndex":2,"settingsHash":1599927394,"maxHealth":400000,"regionSize":2,"flags":0,"damageMultiplier":1.5},{"planetIndex":221,"regionIndex":0,"settingsHash":2024755529,"maxHealth":200000,"regionSize":1,"flags":0,"damageMultiplier":1.5},{"planetIndex":221,"regionIndex":1,"settingsHash":2190098981,"maxHealth":400000,"regionSize":2,"flags":0,"damageMultiplier":1.5},{"planetIndex":226,"regionIndex":0,"settingsHash":452138560,"maxHealth":200000,"regionSize":1,"flags":0,"damageMultiplier":1.5},{"planetIndex":228,"regionIndex":0,"settingsHash":1273177678,"maxHealth":200000,"regionSize":1,"flags":0,"damageMultiplier":1.5},{"planetIndex":228,"regionIndex":1,"settingsHash":3320001654,"maxHealth":100000,"regionSize":0,"flags":0,"damageMultiplier":1.5},{"planetIndex":230,"regionIndex":0,"settingsHash":2472296828,"maxHealth":400000,"regionSize":2,"flags":0,"damageMultiplier":1.5},{"planetIndex":239,"regionIndex":0,"settingsHash":579852265,"maxHealth":600000,"regionSize":3,"flags":0,"damageMultiplier":1.5},{"planetIndex":239,"regionIndex":1,"settingsHash":1999301409,"maxHealth":600000,"regionSize":3,"flags":0,"damageMultiplier":1.5},{"planetIndex":241,"regionIndex":0,"settingsHash":2936987719,"maxHealth":200000,"regionSize":1,"flags":0,"damageMultiplier":1.5},{"planetIndex":241,"regionIndex":1,"settingsHash":1468847276,"maxHealth":400000,"regionSize":2,"flags":0,"damageMultiplier":1.5},{"planetIndex":244,"regionIndex":0,"settingsHash":3036848565,"maxHealth":400000,"regionSize":2,"flags":0,"damageMultiplier":1.5},{"planetIndex":245,"regionIndex":0,"settingsHash":4264188855,"maxHealth":400000,"regionSize":2,"flags":0,"damageMultiplier":1.5},{"planetIndex":245,"regionIndex":1,"settingsHash":2563609963,"maxHealth":600000,"regionSize":3,"flags":0,"damageMultiplier":1.5},{"planetIndex":246,"regionIndex":0,"settingsHash":4253491601,"maxHealth":100000,"regionSize":0,"flags":0,"damageMultiplier":1.5},{"planetIndex":246,"regionIndex":1,"settingsHash":1061744043,"maxHealth":200000,"regionSize":1,"flags":0,"damageMultiplier":1.5},{"planetIndex":246,"regionIndex":2,"settingsHash":3878380748,"maxHealth":200000,"regionSize":1,"flags":0,"damageMultiplier":1.5},{"planetIndex":260,"regionIndex":0,"settingsHash":3380242454,"maxHealth":2000000,"regionSize":3,"flags":1,"damageMultiplier":0},{"planetIndex":260,"regionIndex":1,"settingsHash":2340207578,"maxHealth":1000000,"regionSize":0,"flags":1,"damageMultiplier":0},{"planetIndex":260,"regionIndex":2,"settingsHash":2735744233,"maxHealth":1500000,"regionSize":2,"flags":1,"damageMultiplier":0},{"planetIndex":260,"regionIndex":3,"settingsHash":1512842277,"maxHealth":1250000,"regionSize":1,"flags":1,"damageMultiplier":0},{"planetIndex":260,"regionIndex":4,"settingsHash":2577020579,"maxHealth":1000000,"regionSize":0,"flags":1,"damageMultiplier":0},{"planetIndex":260,"regionIndex":5,"settingsHash":1475859103,"maxHealth":1500000,"regionSize":2,"flags":1,"damageMultiplier":0},{"planetIndex":260,"regionIndex":6,"settingsHash":2634960640,"maxHealth":1250000,"regionSize":1,"flags":1,"damageMultiplier":0},{"planetIndex":260,"regionIndex":7,"settingsHash":3404329179,"maxHealth":1250000,"regionSize":1,"flags":1,"damageMultiplier":0}]}